podite/__init__.py
podite/_utils.py
podite/bytes.py
podite/catalogs.py
podite/core.py
podite/decorators.py
podite/errors.py
podite/json.py
podite/py.typed
podite/types/__init__.py
podite/types/array.py
podite/types/atomic.py
podite/types/builtin.py
podite/types/enum.py
podite/types/misc.py
podite/types/rust.py
podite-0.1.2.dist-info/LICENSE
podite-0.1.2.dist-info/WHEEL
podite-0.1.2.dist-info/METADATA
podite-0.1.2.dist-info/RECORD
