Metadata-Version: 2.1
Name: podite
Version: 0.1.2
Summary: What you see is what you get serialization for Plain Old Data
Home-page: https://github.com/JumpCrypto/podite
Author: Nima Hamidi
Author-email: hamidi@alumni.stanford.edu
Requires-Python: >=3.8,<4.0
Classifier: Programming Language :: Python :: 3
Classifier: Programming Language :: Python :: 3.10
Classifier: Programming Language :: Python :: 3.8
Classifier: Programming Language :: Python :: 3.9
